check_bump/__init__.py
check_bump/exit_codes.py
check_bump/git.py
check_bump/path.py
check_bump/util.py
check_bump/methods/__init__.py
check_bump/methods/regex.py
check_bump/methods/toml.py
check_bump/methods/touch.py
check_bump-1.1.1.dist-info/LICENSE
check_bump-1.1.1.dist-info/METADATA
check_bump-1.1.1.dist-info/WHEEL
check_bump-1.1.1.dist-info/entry_points.txt
check_bump-1.1.1.dist-info/top_level.txt
check_bump-1.1.1.dist-info/RECORD
