Metadata-Version: 2.2
Name: check-bump
Version: 1.1.1
Summary: Check if pyproject.toml version was bumped
Author-email: Radoslaw Gryta <radek.gryta@gmail.com>
Project-URL: Homepage, https://github.com/rgryta/Check-Bump
Project-URL: Bug Tracker, https://github.com/rgryta/Check-Bump/issues
Keywords: versioning,check,CI,CD,version,bump
Classifier: Programming Language :: Python :: 3
Classifier: License :: OSI Approved :: MIT License
Classifier: Operating System :: OS Independent
Requires-Python: >=3.11
License-File: LICENSE
Requires-Dist: tomlkit
Requires-Dist: jsonpath-ng
Provides-Extra: dev
Requires-Dist: staging; extra == "dev"
Requires-Dist: black; extra == "dev"
Requires-Dist: isort; extra == "dev"
Requires-Dist: noprint; extra == "dev"
Requires-Dist: pylint; extra == "dev"
Requires-Dist: bump-my-version; extra == "dev"
Requires-Dist: mock; extra == "dev"
Requires-Dist: pytest; extra == "dev"
Requires-Dist: pytest-sugar; extra == "dev"
Requires-Dist: pytest-xdist; extra == "dev"
Requires-Dist: pytest-asyncio; extra == "dev"
Requires-Dist: pytest-timeout; extra == "dev"
Requires-Dist: coverage[toml]; extra == "dev"
